odoo/addons/product_template_multi_link_date_span/README.rst
odoo/addons/product_template_multi_link_date_span/__init__.py
odoo/addons/product_template_multi_link_date_span/__manifest__.py
odoo/addons/product_template_multi_link_date_span/i18n/product_template_multi_link_date_span.pot
odoo/addons/product_template_multi_link_date_span/models/__init__.py
odoo/addons/product_template_multi_link_date_span/models/product_template_link.py
odoo/addons/product_template_multi_link_date_span/models/product_template_link_type.py
odoo/addons/product_template_multi_link_date_span/readme/CONTRIBUTORS.rst
odoo/addons/product_template_multi_link_date_span/readme/CREDITS.rst
odoo/addons/product_template_multi_link_date_span/readme/DESCRIPTION.rst
odoo/addons/product_template_multi_link_date_span/static/description/icon.png
odoo/addons/product_template_multi_link_date_span/static/description/index.html
odoo/addons/product_template_multi_link_date_span/tests/__init__.py
odoo/addons/product_template_multi_link_date_span/tests/test_product_template_link_date_span.py
odoo/addons/product_template_multi_link_date_span/views/product_template_link_type_view.xml
odoo/addons/product_template_multi_link_date_span/views/product_template_link_view.xml
odoo14_addon_product_template_multi_link_date_span-14.0.1.1.0.dist-info/METADATA
odoo14_addon_product_template_multi_link_date_span-14.0.1.1.0.dist-info/WHEEL
odoo14_addon_product_template_multi_link_date_span-14.0.1.1.0.dist-info/top_level.txt
odoo14_addon_product_template_multi_link_date_span-14.0.1.1.0.dist-info/RECORD
