Metadata-Version: 2.1
Name: odoo14-addon-product-template-multi-link-date-span
Version: 14.0.1.1.0
Summary: Add an optional date span for when a link is active.
Home-page: https://github.com/OCA/e-commerce
Author: Camptocamp, Odoo Community Association (OCA)
Author-email: support@odoo-community.org
License: AGPL-3
Platform: UNKNOWN
Classifier: Programming Language :: Python
Classifier: Framework :: Odoo
Classifier: License :: OSI Approved :: GNU Affero General Public License v3
Requires-Python: >=3.6
Requires-Dist: odoo14-addon-product-template-multi-link
Requires-Dist: odoo (<14.1dev,>=14.0a)
